build.py-1.0.0.dist-info/METADATA
build.py-1.0.0.dist-info/RECORD
build.py-1.0.0.dist-info/WHEEL
build.py-1.0.0.dist-info/top_level.txt
lang/__init__.py
lang/python.py
util/__init__.py
util/builder.py
util/builtins.py
util/dynamic.py
util/io.py
util/preprocessor.py
