Metadata-Version: 2.1
Name: build.py
Version: 1.0.0
Summary: A build system
Home-page: https://github.com/Ma124/build.py
Author: Ma_124
Author-email: ma_124@outlook.com
License: UNKNOWN
Platform: UNKNOWN
Classifier: Programming Language :: Python :: 3
Classifier: License :: OSI Approved :: MIT License
Classifier: Operating System :: OS Independent
